pyconverters_newsml/IPTC-MediaTopic-NewsCodes.xlsx
pyconverters_newsml/__init__.py
pyconverters_newsml/newsml.py
pyconverters_newsml-0.5.250.dist-info/entry_points.txt
pyconverters_newsml-0.5.250.dist-info/licenses/LICENSE
pyconverters_newsml-0.5.250.dist-info/WHEEL
pyconverters_newsml-0.5.250.dist-info/METADATA
pyconverters_newsml-0.5.250.dist-info/RECORD
